nmslib_viz/__init__.py
nmslib_viz/config.py
nmslib_viz/file_manager.py
nmslib_viz/nmslib.py
nmslib_viz/pca.py
nmslib_viz/plot.py
nmslib_viz-1.0.1.data/scripts/nmslib-viz
nmslib_viz-1.0.1.dist-info/LICENSE
nmslib_viz-1.0.1.dist-info/METADATA
nmslib_viz-1.0.1.dist-info/WHEEL
nmslib_viz-1.0.1.dist-info/top_level.txt
nmslib_viz-1.0.1.dist-info/RECORD
