Metadata-Version: 2.1
Name: nmslib-viz
Version: 1.0.1
Summary: NMSLIB visualization tool
Home-page: https://github.com/AlbertSuarez/nmslib-viz
Author: AlbertSuarez
Author-email: alsumo95@gmail.com
License: Apache-2.0
Keywords: nmslib visualization graph
Platform: UNKNOWN
Classifier: Programming Language :: Python :: 3
Classifier: Operating System :: OS Independent
Requires-Dist: nmslib (==2.0.5)
Requires-Dist: numpy (==1.18.1)
Requires-Dist: matplotlib (==3.2.0)
Requires-Dist: scikit-learn (==0.22.2.post1)
